wikipedia2vec/__init__.py
wikipedia2vec/cli.py
wikipedia2vec/dictionary.cpp
wikipedia2vec/dictionary.pxd
wikipedia2vec/dictionary.pyx
wikipedia2vec/dump_db.cpp
wikipedia2vec/dump_db.pxd
wikipedia2vec/dump_db.pyx
wikipedia2vec/link_graph.cpp
wikipedia2vec/link_graph.pxd
wikipedia2vec/link_graph.pyx
wikipedia2vec/mention_db.cpp
wikipedia2vec/mention_db.pxd
wikipedia2vec/mention_db.pyx
wikipedia2vec/wikipedia2vec.cpp
wikipedia2vec/wikipedia2vec.pyx
wikipedia2vec/utils/__init__.py
wikipedia2vec/utils/random.cpp
wikipedia2vec/utils/random.pxd
wikipedia2vec/utils/random.pyx
wikipedia2vec/utils/wiki_dump_reader.cpp
wikipedia2vec/utils/wiki_dump_reader.pyx
wikipedia2vec/utils/wiki_page.cpp
wikipedia2vec/utils/wiki_page.pxd
wikipedia2vec/utils/wiki_page.pyx
wikipedia2vec/utils/sentence_detector/__init__.py
wikipedia2vec/utils/sentence_detector/icu_sentence_detector.cpp
wikipedia2vec/utils/sentence_detector/icu_sentence_detector.pyx
wikipedia2vec/utils/sentence_detector/sentence.cpp
wikipedia2vec/utils/sentence_detector/sentence.pxd
wikipedia2vec/utils/sentence_detector/sentence.pyx
wikipedia2vec/utils/tokenizer/__init__.py
wikipedia2vec/utils/tokenizer/base_tokenizer.cpp
wikipedia2vec/utils/tokenizer/base_tokenizer.pxd
wikipedia2vec/utils/tokenizer/base_tokenizer.pyx
wikipedia2vec/utils/tokenizer/icu_tokenizer.cpp
wikipedia2vec/utils/tokenizer/icu_tokenizer.pyx
wikipedia2vec/utils/tokenizer/jieba_tokenizer.cpp
wikipedia2vec/utils/tokenizer/jieba_tokenizer.pyx
wikipedia2vec/utils/tokenizer/mecab_tokenizer.cpp
wikipedia2vec/utils/tokenizer/mecab_tokenizer.pyx
wikipedia2vec/utils/tokenizer/regexp_tokenizer.cpp
wikipedia2vec/utils/tokenizer/regexp_tokenizer.pyx
wikipedia2vec/utils/tokenizer/token.cpp
wikipedia2vec/utils/tokenizer/token.pxd
wikipedia2vec/utils/tokenizer/token.pyx
wikipedia2vecsm-0.2.3.dist-info/LICENSE
wikipedia2vecsm-0.2.3.dist-info/METADATA
wikipedia2vecsm-0.2.3.dist-info/WHEEL
wikipedia2vecsm-0.2.3.dist-info/entry_points.txt
wikipedia2vecsm-0.2.3.dist-info/top_level.txt
wikipedia2vecsm-0.2.3.dist-info/RECORD
